[
  {
    "type": "meta",
    "message": "This file is managed by Tracepaper"
  },
  {
    "name": "firstName",
    "title": "Firstname",
    "type": "String",
    "pattern": "",
    "placeholder": "",
    "default": ""
  },
  {
    "name": "lastName",
    "title": "Lastname",
    "type": "String",
    "pattern": "",
    "placeholder": "",
    "default": ""
  },
  {
    "name": "year",
    "title": "Year",
    "type": "String",
    "pattern": "^(?:20)\\d{2}$",
    "placeholder": "",
    "default": ""
  },
  {
    "name": "email",
    "title": "Email",
    "type": "String",
    "pattern": "^[\\w\\-\\.]+@([\\w\\-]+\\.)+[\\w\\-]{2,4}$",
    "placeholder": "",
    "default": ""
  },
  {
    "name": "attendingLunch",
    "title": "Attendinglunch",
    "type": "Boolean",
    "pattern": "",
    "placeholder": "",
    "default": ""
  },
  {
    "name": "attendingAfterEventDrinks",
    "title": "Attendingaftereventdrinks",
    "type": "Boolean",
    "pattern": "",
    "placeholder": "",
    "default": ""
  },
  {
    "name": "dietaryNotes",
    "title": "Dietarynotes",
    "type": "String",
    "pattern": "",
    "placeholder": "",
    "default": ""
  },
  {
    "name": "subscribeToNewsletter",
    "title": "Subscribetonewsletter",
    "type": "String",
    "pattern": "",
    "placeholder": "",
    "default": ""
  },
  {
    "name": "nuUpsilonUpsilonOmicron",
    "title": "Nuupsilonupsilonomicron",
    "type": "String",
    "pattern": "",
    "placeholder": "",
    "default": ""
  },
  {
    "name": "breakouts",
    "title": "Breakouts",
    "type": "nested",
    "fields": [
      {
        "name": "id",
        "title": "Id",
        "type": "String",
        "pattern": "",
        "placeholder": "",
        "default": ""
      }
    ]
  }
]